// class version 52.0 (52)
// access flags 0x21
public class Harness implements edu/columbia/cs/psl/phosphor/struct/TaintedWithObjTag {


  @Ledu/columbia/cs/psl/phosphor/runtime/TaintInstrumented;() // invisible

  // access flags 0x1A
  private final static Ljava/lang/String; HARNESS_PATH = "harness/"

  // access flags 0x1A
  private final static Ljava/lang/String; HARNESS_CLASS = "org.dacapo.harness.TestHarness"

  // access flags 0x1A
  private final static Ljava/lang/String; HARNESS_METHOD = "main"

  // access flags 0x1A
  private final static Ljava/lang/String; CALLBACK_CLASSPATH_PROPERTY = "dacapo.callback.classpath"

  // access flags 0x1
  public <init>()V
   L0
   L1
    ALOAD 0
    GETSTATIC java/lang/System.err : Ljava/io/PrintStream;
    LDC "[+] <init> | ()V"
    INVOKEVIRTUAL java/io/PrintStream.println (Ljava/lang/String;)V
    INVOKESPECIAL java/lang/Object.<init> ()V
    RETURN
   L2
    MAXSTACK = 103
    MAXLOCALS = 1

  // access flags 0x9
  public static main([Ljava/lang/String;)V throws java/lang/Exception 
   L0
   L1
    GETSTATIC java/lang/System.err : Ljava/io/PrintStream;
    LDC "[+] makeHarnessClassLoader | ()Ljava/lang/ClassLoader;"
    INVOKEVIRTUAL java/io/PrintStream.println (Ljava/lang/String;)V
    INVOKESTATIC Harness.makeHarnessClassLoader ()Ljava/lang/ClassLoader;
    ASTORE 1
    GETSTATIC java/lang/System.err : Ljava/io/PrintStream;
    LDC "[+] currentThread | ()Ljava/lang/Thread;"
    INVOKEVIRTUAL java/io/PrintStream.println (Ljava/lang/String;)V
    INVOKESTATIC java/lang/Thread.currentThread ()Ljava/lang/Thread;
    ALOAD 1
    GETSTATIC java/lang/System.err : Ljava/io/PrintStream;
    LDC "[+] setContextClassLoader | (Ljava/lang/ClassLoader;)V"
    INVOKEVIRTUAL java/io/PrintStream.println (Ljava/lang/String;)V
    INVOKEVIRTUAL java/lang/Thread.setContextClassLoader (Ljava/lang/ClassLoader;)V
    ALOAD 1
    LDC "org.dacapo.harness.TestHarness"
    GETSTATIC java/lang/System.err : Ljava/io/PrintStream;
    LDC "[+] loadClass | (Ljava/lang/String;)Ljava/lang/Class;"
    INVOKEVIRTUAL java/io/PrintStream.println (Ljava/lang/String;)V
    INVOKEVIRTUAL java/lang/ClassLoader.loadClass (Ljava/lang/String;)Ljava/lang/Class;
    ASTORE 2
    ALOAD 2
    LDC "main"
    ICONST_1
    ANEWARRAY java/lang/Class
    DUP
    ICONST_0
    LDC [Ljava/lang/String;.class
    AASTORE
    GETSTATIC java/lang/System.err : Ljava/io/PrintStream;
    LDC "[+] getDeclaredMethod | (Ljava/lang/String;[Ljava/lang/Class;)Ljava/lang/reflect/Method;"
    INVOKEVIRTUAL java/io/PrintStream.println (Ljava/lang/String;)V
    ICONST_1
    INVOKESTATIC edu/columbia/cs/psl/phosphor/runtime/ReflectionMasker.getDeclaredMethod (Ljava/lang/Class;Ljava/lang/String;[Ljava/lang/Class;Z)Ljava/lang/reflect/Method;
    ASTORE 3
    ALOAD 3
    ACONST_NULL
    ICONST_1
    ANEWARRAY java/lang/Object
    DUP
    ICONST_0
    ALOAD 0
    AASTORE
    GETSTATIC java/lang/System.err : Ljava/io/PrintStream;
    LDC "[+] invoke | (Ljava/lang/Object;[Ljava/lang/Object;)Ljava/lang/Object;"
    INVOKEVIRTUAL java/io/PrintStream.println (Ljava/lang/String;)V
    ICONST_1
    INVOKESTATIC edu/columbia/cs/psl/phosphor/runtime/ReflectionMasker.fixAllArgs (Ljava/lang/reflect/Method;Ljava/lang/Object;[Ljava/lang/Object;Z)Ledu/columbia/cs/psl/phosphor/struct/MethodInvoke;
    DUP
    GETFIELD edu/columbia/cs/psl/phosphor/struct/MethodInvoke.m : Ljava/lang/reflect/Method;
    SWAP
    DUP
    GETFIELD edu/columbia/cs/psl/phosphor/struct/MethodInvoke.o : Ljava/lang/Object;
    SWAP
    GETFIELD edu/columbia/cs/psl/phosphor/struct/MethodInvoke.a : [Ljava/lang/Object;
    INVOKEVIRTUAL java/lang/reflect/Method.invoke (Ljava/lang/Object;[Ljava/lang/Object;)Ljava/lang/Object;
    DUP
    INSTANCEOF edu/columbia/cs/psl/phosphor/struct/TaintedPrimitiveWithObjTag
    IFEQ L2
    CHECKCAST edu/columbia/cs/psl/phosphor/struct/TaintedPrimitiveWithObjTag
    INVOKEVIRTUAL edu/columbia/cs/psl/phosphor/struct/TaintedPrimitiveWithObjTag.toPrimitiveType ()Ljava/lang/Object;
   L2
   FRAME FULL [[Ljava/lang/String; java/lang/ClassLoader java/lang/Class java/lang/reflect/Method] [java/lang/Object]
    POP
    ACONST_NULL
    ICONST_0
    GETSTATIC java/lang/System.err : Ljava/io/PrintStream;
    LDC "[+] exit | (I)V"
    INVOKEVIRTUAL java/io/PrintStream.println (Ljava/lang/String;)V
    INVOKESTATIC java/lang/System.exit$$PHOSPHORTAGGED (Ledu/columbia/cs/psl/phosphor/runtime/Taint;I)V
    RETURN
   L3
    MAXSTACK = 106
    MAXLOCALS = 4

  // access flags 0xA
  private static makeHarnessClassLoader()Ljava/lang/ClassLoader; throws java/net/MalformedURLException java/net/URISyntaxException 
