// class version 52.0 (52)
// access flags 0x21
public class Basic implements edu/columbia/cs/psl/phosphor/struct/TaintedWithIntTag {


  @Ledu/columbia/cs/psl/phosphor/runtime/TaintInstrumented;() // invisible
  // compiled from: Basic.java

  // access flags 0x1
  public <init>()V
   L0
   L1
   L2
    LINENUMBER 17 L2
    ALOAD 0
    INVOKESPECIAL java/lang/Object.<init> ()V
    RETURN
   L3
    MAXSTACK = 101
    MAXLOCALS = 1

  // access flags 0x9
  public static main([Ljava/lang/String;)V
   L0
   L1
    NEW edu/columbia/cs/psl/phosphor/struct/TaintedIntWithIntTag
    DUP
    INVOKESPECIAL edu/columbia/cs/psl/phosphor/struct/TaintedIntWithIntTag.<init> ()V
    ASTORE 1
   L2
   L3
    LINENUMBER 19 L3
    NEW Human
    DUP
    LDC "ABC"
    INVOKESPECIAL Human.<init> (Ljava/lang/String;)V
    ASTORE 2
   L4
    LINENUMBER 20 L4
    GETSTATIC java/lang/System.out : Ljava/io/PrintStream;
    ALOAD 2
    INVOKEVIRTUAL Human.getName ()Ljava/lang/String;
    INVOKEVIRTUAL java/io/PrintStream.println (Ljava/lang/String;)V
   L5
    LINENUMBER 21 L5
    ICONST_0
    ICONST_2
    ALOAD 1
    INVOKESTATIC Basic.foo$$PHOSPHORTAGGED (IILedu/columbia/cs/psl/phosphor/struct/TaintedIntWithIntTag;)Ledu/columbia/cs/psl/phosphor/struct/TaintedIntWithIntTag;
    GETFIELD edu/columbia/cs/psl/phosphor/struct/TaintedIntWithIntTag.val : I
    POP
   L6
    LINENUMBER 22 L6
    RETURN
   L7
    MAXSTACK = 103
    MAXLOCALS = 3

  // access flags 0x9
  public static foo$$PHOSPHORTAGGED(IILedu/columbia/cs/psl/phosphor/struct/TaintedIntWithIntTag;)Ledu/columbia/cs/psl/phosphor/struct/TaintedIntWithIntTag;
   L0
   L1
   L2
    LINENUMBER 25 L2
    GETSTATIC java/lang/System.out : Ljava/io/PrintStream;
    LDC "in foo()"
    INVOKEVIRTUAL java/io/PrintStream.println (Ljava/lang/String;)V
   L3
    LINENUMBER 26 L3
    ILOAD 0
    ILOAD 1
    ICONST_0
    ICONST_2
   L4
    ISTORE 3
    SWAP
    ILOAD 3
   L5
    IADD
    DUP_X2
    POP
    IOR
    SWAP
    ALOAD 2
    SWAP
    PUTFIELD edu/columbia/cs/psl/phosphor/struct/TaintedIntWithIntTag.val : I
    ALOAD 2
    SWAP
    PUTFIELD edu/columbia/cs/psl/phosphor/struct/TaintedIntWithIntTag.taint : I
    ALOAD 2
    ARETURN
   L6
    MAXSTACK = 102
    MAXLOCALS = 4

  // access flags 0x18
  final static J serialVersionUID = -8119405352596384264

  // access flags 0x1
  public I PHOSPHOR_TAG = 0

  // access flags 0x1
  public I $$PHOSPHOR_MARK = -2147483648

  // access flags 0x9
  public static I serialVersionUIDPHOSPHOR_TAG = 0

  // access flags 0x1001
  public synthetic equals(Ljava/lang/Object;)Z
   L0
    ALOAD 0
    ALOAD 1
    INVOKESPECIAL java/lang/Object.equals (Ljava/lang/Object;)Z
   L1
    IRETURN
    LOCALVARIABLE this LBasic; L0 L1 0
    LOCALVARIABLE other Ljava/lang/Object; L0 L1 1
    MAXSTACK = 0
    MAXLOCALS = 0

  // access flags 0x1001
  public synthetic hashCode()I
   L0
    ALOAD 0
    INVOKESPECIAL java/lang/Object.hashCode ()I
   L1
    IRETURN
    LOCALVARIABLE this LBasic; L0 L1 0
    MAXSTACK = 0
    MAXLOCALS = 0

  // access flags 0x1
  public getPHOSPHOR_TAG()I
    ALOAD 0
    GETFIELD Basic.PHOSPHOR_TAG : I
    IRETURN
    MAXSTACK = 0
    MAXLOCALS = 0

  // access flags 0x1
  public setPHOSPHOR_TAG(I)V
    ALOAD 0
    ILOAD 1
    PUTFIELD Basic.PHOSPHOR_TAG : I
    RETURN
    MAXSTACK = 0
    MAXLOCALS = 0

  // access flags 0x9
  public static foo(I)I
   L0
   L1
    NEW edu/columbia/cs/psl/phosphor/struct/TaintedIntWithIntTag
    DUP
    INVOKESPECIAL edu/columbia/cs/psl/phosphor/struct/TaintedIntWithIntTag.<init> ()V
    ASTORE 1
   L2
    LINENUMBER 0 L2
    ICONST_0
    ILOAD 0
    ALOAD 1
    INVOKESTATIC Basic.foo$$PHOSPHORTAGGED (IILedu/columbia/cs/psl/phosphor/struct/TaintedIntWithIntTag;)Ledu/columbia/cs/psl/phosphor/struct/TaintedIntWithIntTag;
    GETFIELD edu/columbia/cs/psl/phosphor/struct/TaintedIntWithIntTag.val : I
   L3
    IRETURN
   L4
    MAXSTACK = 3
    MAXLOCALS = 2

  // access flags 0x1
  public equals$$PHOSPHORTAGGED(Ljava/lang/Object;Ledu/columbia/cs/psl/phosphor/struct/TaintedBooleanWithIntTag;)Ledu/columbia/cs/psl/phosphor/struct/TaintedBooleanWithIntTag;
   L0
   L1
    ALOAD 0
    ALOAD 1
    DUP
    DUP
    INSTANCEOF [Ledu/columbia/cs/psl/phosphor/struct/LazyArrayIntTags;
    SWAP
    INSTANCEOF edu/columbia/cs/psl/phosphor/struct/LazyArrayIntTags
    IOR
    IFEQ L2
    INVOKESTATIC edu/columbia/cs/psl/phosphor/struct/multid/MultiDTaintedArrayWithIntTag.unboxRaw (Ljava/lang/Object;)Ljava/lang/Object;
   L2
   FRAME FULL [Basic java/lang/Object edu/columbia/cs/psl/phosphor/struct/TaintedBooleanWithIntTag] [Basic java/lang/Object]
    INVOKESPECIAL Basic.equals (Ljava/lang/Object;)Z
    ALOAD 2
    SWAP
    PUTFIELD edu/columbia/cs/psl/phosphor/struct/TaintedBooleanWithIntTag.val : Z
    ALOAD 2
    ICONST_0
    PUTFIELD edu/columbia/cs/psl/phosphor/struct/TaintedBooleanWithIntTag.taint : I
    ALOAD 2
   L3
    ARETURN
    LOCALVARIABLE this LBasic; L1 L3 0
    LOCALVARIABLE phosphorNativeWrapArg1 Ljava/lang/Object; L1 L3 1
    LOCALVARIABLE phosphorReturnHolder Ledu/columbia/cs/psl/phosphor/struct/TaintedBooleanWithIntTag; L1 L3 2
   L4
    MAXSTACK = 4
    MAXLOCALS = 3

  // access flags 0x1
  public hashCode$$PHOSPHORTAGGED(Ledu/columbia/cs/psl/phosphor/struct/TaintedIntWithIntTag;)Ledu/columbia/cs/psl/phosphor/struct/TaintedIntWithIntTag;
   L0
   L1
    ALOAD 0
    INVOKESPECIAL Basic.hashCode ()I
    ALOAD 1
    SWAP
    PUTFIELD edu/columbia/cs/psl/phosphor/struct/TaintedIntWithIntTag.val : I
    ALOAD 1
    ICONST_0
    PUTFIELD edu/columbia/cs/psl/phosphor/struct/TaintedIntWithIntTag.taint : I
    ALOAD 1
   L2
    ARETURN
    LOCALVARIABLE this LBasic; L1 L2 0
    LOCALVARIABLE phosphorReturnHolder Ledu/columbia/cs/psl/phosphor/struct/TaintedIntWithIntTag; L1 L2 1
   L3
    MAXSTACK = 2
    MAXLOCALS = 2

  // access flags 0x1
  public getClass$$PHOSPHORTAGGED()Ljava/lang/Class;
   L0
   L1
    ALOAD 0
    INVOKESPECIAL Basic.getClass ()Ljava/lang/Class;
   L2
    ARETURN
    LOCALVARIABLE this LBasic; L1 L2 0
   L3
    MAXSTACK = 1
    MAXLOCALS = 1

  // access flags 0x1
  public toString$$PHOSPHORTAGGED()Ljava/lang/String;
   L0
   L1
    ALOAD 0
    INVOKESPECIAL Basic.toString ()Ljava/lang/String;
   L2
    ARETURN
    LOCALVARIABLE this LBasic; L1 L2 0
   L3
    MAXSTACK = 1
    MAXLOCALS = 1
}
